MANIFEST.in
README.rst
setup.py
bin/test-script
metering/DataFunctions.py
metering/GeoFunctions.py
metering/__init__.py
metering/arcgis_credentials.py
metering/command_line.py
metering/equipment.py
metering/exports.py
metering/measurements.py
metering/plot.py
metering/psyc.py
metering/stats.py
metering/weather.py
metering.egg-info/PKG-INFO
metering.egg-info/SOURCES.txt
metering.egg-info/dependency_links.txt
metering.egg-info/entry_points.txt
metering.egg-info/not-zip-safe
metering.egg-info/top_level.txt
metering/data/Exports/HOBOWare/M0003-Worcester-10064511-20150417-091745.csv
metering/data/Exports/HOBOWare/M0100-West-10181391 (1).csv
metering/data/Exports/HOBOWare/M0100-West-10181391 (2).csv
metering/data/Exports/HOBOWare/M0100-West-10365288-20150413-125200.csv
metering/data/Exports/HOBOWare/MG074-Manhattan-10580517-20160922-222222.csv
metering/data/Images/Directory.png
metering/data/Notebooks/HTML/Metering+Introduction.html
metering/data/weather/input/options.csv
metering/data/weather/input/stations.csv