Metadata-Version: 1.0
Name: metering
Version: 0.1.10
Summary: Under development.
Home-page: UNKNOWN
Author: c__mite
Author-email: UNKNOWN
License: none
Platform: UNKNOWN
